CMakeLists.txt
MANIFEST.in
README.md
setup.py
lib/gameboycore/.git
lib/gameboycore/.gitignore
lib/gameboycore/.gitmodules
lib/gameboycore/.travis.yml
lib/gameboycore/CMakeLists.txt
lib/gameboycore/LICENSE.md
lib/gameboycore/README.md
lib/gameboycore/appveyor.yml
lib/gameboycore/cmake/get-version-config.cmake
lib/gameboycore/cmake/version-config.cmake
lib/gameboycore/cmake/Modules/CodeCoverage.cmake
lib/gameboycore/cmake/Modules/FindSFML.cmake
lib/gameboycore/docs/Doxyfile.in
lib/gameboycore/docs/DoxygenLayout.xml
lib/gameboycore/docs/customdoxygen.css
lib/gameboycore/docs/docs.svg
lib/gameboycore/docs/doxy-boot.js
lib/gameboycore/docs/footer.html
lib/gameboycore/docs/header.html
lib/gameboycore/scripts/coverage
lib/gameboycore/scripts/travis_deploy_docs
lib/gameboycore/src/CMakeLists.txt
lib/gameboycore/src/gameboycore/CMakeLists.txt
lib/gameboycore/src/gameboycore/include/gameboycore/alu.h
lib/gameboycore/src/gameboycore/include/gameboycore/apu.h
lib/gameboycore/src/gameboycore/include/gameboycore/cartinfo.h
lib/gameboycore/src/gameboycore/include/gameboycore/channel.h
lib/gameboycore/src/gameboycore/include/gameboycore/cpu.h
lib/gameboycore/src/gameboycore/include/gameboycore/gameboycore.h
lib/gameboycore/src/gameboycore/include/gameboycore/gameboycore_api.h
lib/gameboycore/src/gameboycore/include/gameboycore/gpu.h
lib/gameboycore/src/gameboycore/include/gameboycore/interrupt_provider.h
lib/gameboycore/src/gameboycore/include/gameboycore/joypad.h
lib/gameboycore/src/gameboycore/include/gameboycore/link.h
lib/gameboycore/src/gameboycore/include/gameboycore/link_cable.h
lib/gameboycore/src/gameboycore/include/gameboycore/mbc.h
lib/gameboycore/src/gameboycore/include/gameboycore/mbc1.h
lib/gameboycore/src/gameboycore/include/gameboycore/mbc2.h
lib/gameboycore/src/gameboycore/include/gameboycore/mbc3.h
lib/gameboycore/src/gameboycore/include/gameboycore/mbc5.h
lib/gameboycore/src/gameboycore/include/gameboycore/memorymap.h
pygameboycore.egg-info/PKG-INFO
pygameboycore.egg-info/SOURCES.txt
pygameboycore.egg-info/dependency_links.txt
pygameboycore.egg-info/not-zip-safe
pygameboycore.egg-info/top_level.txt
