Metadata-Version: 1.0
Name: pygameboycore
Version: 0.0.4
Summary: Python bindings for GameboyCore
Home-page: UNKNOWN
Author: Cory Monroe
Author-email: cory.s.monroe@gmail.com
License: UNKNOWN
Platform: UNKNOWN
